<Q><title>申请青年基金，能不能用博士后特别资助的申请基金的内容</title><apdx>今年中了一个博士后的特别资助，最近在写青年基金，不知道能不能用博士后那个基金的申请内容？<apdx></Q>
<A><answer>没问题，最好稍微改改</answer><quality>0</quality><upvote>0</upvote><answer>完全一致必须不行~</answer><quality>0</quality><upvote>0</upvote><answer>为啥不行？</answer><quality>0</quality><upvote>0</upvote></A>
<url>http://muchong.com/t-2855249-1</url>
<Q><title>发现错误，解除保护后，摘要部分无法修改</title><apdx>检查保护后，发现有错误<br>又接触保护了<br>但是摘要部分无法修改，包括预算的备注部分<br>有虫子能帮忙解决吗？<br>[]<apdx></Q>
<A><answer>这个问题没有遇到过，询问一下负责人吧</answer><quality>0</quality><upvote>0</upvote><answer>解除保护再修改</answer><quality>0</quality><upvote>0</upvote><answer>解除后可以修改的啊</answer><quality>0</quality><upvote>0</upvote><answer>先删除，再添加，试试。有时候是因为字数满了。</answer><quality>0</quality><upvote>1</upvote><answer>都不行啊，摘要部分连光标都点不进去</answer><quality>0</quality><upvote>0</upvote><answer>双击。。</answer><quality>0</quality><upvote>0</upvote><answer>双击没有任何作用<br>不知道是不是因为VISTA系统的问题</answer><quality>0</quality><upvote>0</upvote><answer>解除保护就可以了吧</answer><quality>0</quality><upvote>0</upvote><answer>就是在解除保护后啊，正文部分可以修改，就是摘要和预算里备注部分改不了</answer><quality>0</quality><upvote>0</upvote><answer>解除保护后可以的！点摘要部分，它就全部变成阴影的了，然后就可以删除了，你把你的再粘贴上去就行了。不过如果超过了她规定的400个字符，就只能进去前400个字符了！注意是指的字符数，而不是字数！我当时就以为是字数。</answer><quality>0</quality><upvote>1</upvote><answer>解除保护.基金网上关于操作部分有操作方法.</answer><quality>0</quality><upvote>1</upvote><answer>无奈了，我已经打算重新填写了</answer><quality>0</quality><upvote>0</upvote><answer>我也遇到同样的问题。</answer><quality>0</quality><upvote>0</upvote></A>
<url>http://muchong.com/t-1873618-1</url>
<Q><title>请教计划书无法检查保护</title><apdx>计划书无法检查保护，总是显示<br>“ISIS_PJPLAN_DOC.dll必需和计划书在同一目录下才能检查<br>保护“<br>可是在我的系统里面ISIS_PJPLAN_DOC.dll和计划书明明在同一目录下<br>系统：vista，Word2003<apdx></Q>
<A><answer>我的win7+word2003也出现同样问题，可能是兼容问题</answer><quality>0</quality><upvote>1</upvote><answer>已经解决了，把uac关掉即可</answer><quality>0</quality><upvote>0</upvote><answer>弱弱的问下，啥是uac？</answer><quality>0</quality><upvote>1</upvote></A>
<url>http://muchong.com/t-2334620-1</url>
<Q><title>怎么给申请书起名字，求助啊</title><apdx>请教各位大侠，我有一个非常苦恼的问题：<br>我是做逻辑方面的，也不完全是做逻辑理论，应该是基于逻辑的控制方法方面吧，基于一种新的逻辑研究一种新的控制方法，就比如是基于模糊逻辑的模糊控制方法，在攻读博士期间，我将这种控制方法应用在一种典型的控制实验装置上。<br>现在我想基于博士期间的工作拓展做进一步的研究，并申请国青基，现在有这样的问题：<br>１）    如果单纯是依靠这种控制方法来写本子的话，内容会显得很空洞，所以我选取机器人中的一个控制点作为我的控制对象，我也联合了机器人控制方面的研究成员。<br>２）    但是就出现了这样的问题：我的研究重点是控制方法，而不是机器人，我的强项是控制方法，这种控制方法具有通用性，但是机器人方面是我的弱项。<br>３）    因此，两次申请后，专家的评价都是××机器人的控制问题，对国内外研究现状总结不够，缺乏对所要解决的问题和方法的深入了解。。。<br>我觉得，评价的专家都是机器人控制方面的，而机器人方面是我的弱项，所以在本子中我对这种机器人控制方面的国内外研究现状分析不是很多，重点放在对这种通用控制方法的研究现状上了。<br>呵呵，啰唆地说了这么多，也不知道讲清楚了没有。问题是：<br>1）本子的名字怎么取：（以这个为例：基于递阶滑模的自适应控制及其在一类欠驱动系统中的应用）<br>我前两次的取法都是（假设）：一类欠驱动系统的递阶滑模自适应控制方法研究。<br>是不是这样取名的话，专家的重点就放在了这类欠驱动系统上。而不是后面的控制方法上。<br>如果这样取名的话：基于递阶滑模的自适应控制及其在一类欠驱动系统中的应用，<br>是不是重点就是在控制方法上，但是我就不知道这样的本子应该怎样写（大侠，有这样的本子可以借鉴吗，不胜感激）：<br>1）立项依据：<br>前面都写基于递阶滑模的自适应控制方法的研究现状吗，最后提一下这类欠驱动系统的研究现状；<br>2）研究内容<br>单纯写这种基于递阶滑模的自适应控制方法的研究点，还是结合这类欠驱动系统来写这种控制方法的研究点。<br>    以上就是我非常苦恼的问题，请各位大侠发表你们的意见，谢谢了，非常感谢，真是不知道这种情况该如何去写基金本子。<apdx></Q>
<A><answer>建议：<br>题目：基于XXXXX的控制方法及其在XXXX中的应用研究<br>立项依据：前面写XXXX控制方法的研究现状（XXXX优点），然后重点阐述你的应用实施例的研究现状，显示你的控制方法的先进性和重要性（比如现今的控制方法对你的应用实施例控制效果不好等等），这一部分直接关系到你的东西是否有研究意义。<br>研究内容：当然必须要加入应用实施例，不然你的控制方法是否值得研究都是个问题。（比如，XXXX在工业上有重要的应用，但是迄今为止其控制方法有XXXX缺陷，基于此提出一种新的XXXX控制方法等等）</answer><quality>0</quality><upvote>1</upvote><answer>哦，应该先写你的应用实施例的研究现状，然后引出其控制方法，这样会比较好点</answer><quality>0</quality><upvote>0</upvote><answer>要用题目吸引眼球。</answer><quality>0</quality><upvote>0</upvote><answer>我也有类似的问题，老想从方法去研究某一问题，而方法对很多问题都有一定的通用性，而不是从解决某一问题着手。</answer><quality>0</quality><upvote>1</upvote><answer>看看往年已中基金的名字,会有灵感的</answer><quality>0</quality><upvote>0</upvote><answer>看看往年已中基金的名字,会有灵感的</answer><quality>0</quality><upvote>0</upvote></A>
<url>http://muchong.com/t-2855606-1</url>
<Q><title>nsfc里把脚注与列表都禁掉了，咱办</title><apdx>申请书里不能添加列表，也不能加脚注<br>咱办<apdx></Q>
<A><answer>在正文里面弄好，再插入啊</answer><quality>0</quality><upvote>1</upvote><answer>单独准备word文档，最后再导入即可</answer><quality>0</quality><upvote>1</upvote></A>
<url>http://muchong.com/t-2855756-1</url>
<Q><title>急问:大家交的国家社科活页是4页（A3双面，包含评审表），还是超过4页？谢谢</title><apdx>急问:大家交的国家社科活页是4页（A3双面，包含评审表），还是超过4页？谢谢<apdx></Q>
<A><answer>就是一张A3双面共四页  这个最好问问你们科研处，问别人没用</answer><quality>0</quality><upvote>2</upvote></A>
<url>http://muchong.com/t-2855788-1</url>
<Q><title>请问国家自然基金中海外合作者同意参与项目的说明书模板问题！</title><apdx>大家好，我今年的自然基金项目邀请了一个美国的教授参与。<br>看基金指南上说：“主要参与者中的境外人员被视为以个人身份参与项目申请，如本人未能在纸质申请书上签字，则应通过信件、传真等本人签字的纸质文件，说明本人同意参与该项目申请且履行相关职责，作为附件随纸质申请书一并报送。”<br>现在美国学者要我把邀请函和证明书发给他，他签完字后寄给我。<br>请问大伙，这个“本人同意参与该项目申请且履行相关职责”的说明书应该怎么写啊？有没有什么模板呢？<br>谢谢大家！<br>预祝大伙元宵节快乐！<apdx></Q>
<A><answer>我也有这样的问题,同问,请大家多多指教</answer><quality>0</quality><upvote>1</upvote></A>
<url>http://muchong.com/t-2854117-1</url>
<Q><title>谁能给出权威答案</title><apdx>今年基金限项有了新规定，指南里解释了一大通，但仍然很模糊。<br>最大的疑问是高级职称者，以前从未中过也未参与过基金，<br>今年可以同时以主持身份，申报面上项目和地区基金两个嘛？<br>敬请牛人权威解答！<apdx></Q>
<A><answer>没有禁止应该就是允许的吧</answer><quality>0</quality><upvote>1</upvote><answer>想要权威解答，可以打电话问基金委，答案马上知道。<br>当然，欢迎你把问到的结果告诉大家。</answer><quality>0</quality><upvote>1</upvote><answer>不能相当然，说不定到时候两个项目统统初筛拿下。</answer><quality>0</quality><upvote>0</upvote><answer>关键是，地区项目现在还算不算面上项目的一个分支？<br>过去面上项目=自由申请项目+青年项目+地区项目，现在青年单列了，地区项目俺就不关心了。</answer><quality>0</quality><upvote>1</upvote><answer>只有基金委是权威的</answer><quality>0</quality><upvote>1</upvote><answer>我的理解是可以的，所以今年面上的申请将会异常激烈</answer><quality>0</quality><upvote>1</upvote><answer>如果地区项目也归为面上项目，2个同类型的项目就不能一起申请。这么细的专业问题还得咨询本校科技处。</answer><quality>0</quality><upvote>1</upvote><answer>这个得问基金委！</answer><quality>0</quality><upvote>0</upvote><answer>电话问基金委-------</answer><quality>0</quality><upvote>1</upvote><answer>事关重大，还是找基金委要权威答案吧</answer><quality>0</quality><upvote>1</upvote><answer>还是要问基金委或者申报单位的负责人</answer><quality>0</quality><upvote>1</upvote><answer>Godblessyou!~~~</answer><quality>0</quality><upvote>1</upvote><answer>打电话问是正解</answer><quality>0</quality><upvote>0</upvote><answer>今年完全可以！</answer><quality>0</quality><upvote>0</upvote><answer>面上和地区主持身份每年限报1个，只能二选一</answer><quality>0</quality><upvote>1</upvote><answer>面上和地区只能择其一申报</answer><quality>0</quality><upvote>1</upvote><answer>不可以同时一年申请2个相同类型的基金，至于哪些基金是相同类型的，见基金委的分类！</answer><quality>0</quality><upvote>1</upvote><answer>不可以的，地区基金与面上项目是同一个体系的，二者只能报其一</answer><quality>0</quality><upvote>1</upvote><answer>同类型的只能报一个，限项说明第一条就说了。</answer><quality>0</quality><upvote>1</upvote><answer>咨询发布东西的地方</answer><quality>0</quality><upvote>1</upvote><answer>二选一,hehe</answer><quality>0</quality><upvote>0</upvote><answer>这个应该问基金委，现在他们也上班了</answer><quality>0</quality><upvote>1</upvote><answer>感觉是不行的，呵呵。。最好还是致电基金委，这样最权威</answer><quality>0</quality><upvote>1</upvote><answer>感觉是二选一</answer><quality>0</quality><upvote>0</upvote><answer>我能给出答案，呵呵</answer><quality>0</quality><upvote>1</upvote><answer>问基金委</answer><quality>0</quality><upvote>0</upvote><answer>同时申请没有问题，但是中的机会会少一些。</answer><quality>0</quality><upvote>1</upvote><answer>问基金委吧</answer><quality>0</quality><upvote>0</upvote><answer>不可以</answer><quality>0</quality><upvote>0</upvote><answer>还是问问基金委吧</answer><quality>0</quality><upvote>1</upvote><answer>只有基金委是权威的</answer><quality>0</quality><upvote>1</upvote><answer>基金委是权威,打电话问问他们</answer><quality>0</quality><upvote>1</upvote></A>
<url>http://muchong.com/t-2846926-1</url>
<Q><title>关于项目参加人</title><apdx>项目参加人中，硕士生，博士生，是不是指还没有毕业的啊。<br>如果参加人是硕士学历，讲师职称，在读博士。那算不算博士生这里面呢。<apdx></Q>
<A><answer>也算的。不过可以直接写讲师吧。</answer><quality>0</quality><upvote>1</upvote></A>
<url>http://muchong.com/t-2855132-1</url>
<Q><title>限项问题：共三项挂名，但这个人时间合计超过每年12个月了可以吗？</title><apdx>09年时被挂名，时间写了每年5个月；今年自己申请写时间5个月/年；另一个同学带我的话，每年多长时间合适？如果太少，写上也不合适啊？<br>谢谢！<apdx></Q>
<A><answer>不是正高不是面上，没啥问题把</answer><quality>0</quality><upvote>1</upvote><answer>本人副高，今年要申请的是面上。<br>时间问题，限项说明里好像没有提到啊。<br>请知情者告知，谢谢！</answer><quality>0</quality><upvote>0</upvote><answer>09年被挂名的时候就是高级支撑么？是的话就要注意。</answer><quality>0</quality><upvote>1</upvote></A>
<url>http://muchong.com/t-2853958-1</url>
<Q><title>急求讲师限项问题</title><apdx>今天有一个问题困惑的不行，请虫友们解答一下：<br>本人现在是讲师，明年将评上副高。去年获青年基金，今年开始执行，共三年。今年我没资格申请国家自然基金。老板今年要申请面上基金，期中要挂我作为参加人。然而，最近另外一个学校的牛人托我比较熟悉的一个老师说想挂我参加他今年的项目申请，我知道中级参与不限项，请问如果我答应了，这下我名下就有三项了，当我明年升上副高后，这三项将都还没有结题，那么我在中级职称时参与的这两项到副高时是否还算在内，影不影响我在副高时的申请？  非常着急，希望专业人士解答！<apdx></Q>
<A><answer>限主持一项，其他参与不限，为了确保无误，打电话向基金委确认。</answer><quality>0</quality><upvote>1</upvote><answer>和学校科管部门直接咨询吧</answer><quality>0</quality><upvote>1</upvote><answer>虽说有讲师升副教授记录清空的说法，楼主还是到基金委获取权威答案吧</answer><quality>0</quality><upvote>1</upvote><answer>lz这么有把握，就一定能评上副高？</answer><quality>0</quality><upvote>1</upvote><answer>评上副高后，好像主持不清零，参加清零</answer><quality>0</quality><upvote>1</upvote><answer>应该有把握</answer><quality>0</quality><upvote>0</upvote><answer>受限制吧，似乎明年不能申请</answer><quality>0</quality><upvote>1</upvote><answer>跟你有相同的困惑，不过既然有虫说“讲师升副高参与清零，主持不清零”，我想应该不是空穴来风。<br>建议你向基金委电话问一下，有答案记得告诉我哈。。。</answer><quality>0</quality><upvote>1</upvote><answer>给基金委打哪个电话啊</answer><quality>0</quality><upvote>0</upvote></A>
<url>http://muchong.com/t-2851472-1</url>
<Q><title>讲师，在读博士，没有能力代硕士，学校也没有硕士点。如下青基成员组成合理么。</title><apdx>申请人：讲师，在读博士<br>参加人：5个硕士（两个博士在读），一个副教授。<br>如果不合理，有像我这样情况的，大家都是怎么写的成员构成啊。<br>[]<apdx></Q>
<A><answer>挺费劲吧！！！！！！！！！</answer><quality>0</quality><upvote>0</upvote><answer>我觉得搂主写的人太多了，一般青年基金4-6人就可以了，且带副教授也不是太合适吧，讲师领导副教授？会让人觉得这个副教授水平不行？另外，硕士5个太多了。我一般是加一个讲师，一名博士，两名硕士，共5个人</answer><quality>0</quality><upvote>2</upvote><answer>硕士人太多了</answer><quality>0</quality><upvote>0</upvote><answer>说得有道理，一般青基4-6人足够了，自己讲师的话再加一个研究方向相近的讲师，最好再带一两个博士生，一两个硕士生。如果没有博士生两三个硕士生也行...</answer><quality>0</quality><upvote>1</upvote><answer>其实一个基金，一般就是一个成熟教师待个把讲师/助教，两三个研究生干的！</answer><quality>0</quality><upvote>0</upvote></A>
<url>http://muchong.com/t-2854477-1</url>
<Q><title>关于申请书中，主持人签字问题。</title><apdx>申请青基，但本人不在学校，交纸质申请书时，请别人代签字，也就是让别人模仿我签字可以么。<apdx></Q>
<A><answer>这种事情干嘛说出来，偷偷的做就是了，只要不是一模一样！关键是你的本子是自己写的就行！做到问心无愧！！！</answer><quality>0</quality><upvote>0</upvote><answer>:P:P:P:P:P:P:P:P:P:P:P:P:P:P:):):):):):):):):):):):):):):):):):):):):):):):):)</answer><quality>0</quality><upvote>0</upvote><answer>[quote]Originallypostedbyat2011-02-1508:26:21:<br>这种事情干嘛说出来，偷偷的做就是了，只要不是一模一样！关键是你的本子是自己写的就行！做到问心无愧！！！[/quo<br>呵呵。有道理。谢谢</answer><quality>0</quality><upvote>0</upvote><answer>小声点你可以把所有人的字都代签了！只要和人家沟通过，没关系的！而且出现了超项的问题，基金委是根本不看签名的是否一致的！只要名字出现在申报书中就算，在中国，手签字不算数！别人我不告诉！<br>[]</answer><quality>0</quality><upvote>1</upvote><answer>你应该明白怎么做了，我就不多说了，祝好运！</answer><quality>0</quality><upvote>1</upvote><answer>讲究人，够意思。</answer><quality>0</quality><upvote>0</upvote><answer>这人真老实</answer><quality>0</quality><upvote>0</upvote><answer>LZ是GG还是MM？纯纯的，呵呵！</answer><quality>0</quality><upvote>1</upvote></A>
<url>http://muchong.com/t-2854691-1</url>
<Q><title>NSFC2011proposal.exe安装问题</title><apdx>初稿已经完成了，突然间想起来，当初下载NSFC2011proposal.exe后，没有双击安装，而是直接右键解压缩，貌似运行一切正常，请问有没有谁遇到过，能否解答一下，谢谢！<apdx></Q>
<A><answer>本来就是自解压文件</answer><quality>0</quality><upvote>0</upvote><answer>我在xp中下载后还需安装，在Vista中解压缩就可以了</answer><quality>0</quality><upvote>1</upvote><answer>win7双击安装的，一切正常</answer><quality>0</quality><upvote>1</upvote></A>
<url>http://muchong.com/t-2854296-1</url>
<Q><title>参加国家社科基金与国家自然科学基金的限项问题？</title><apdx>有一个朋友，参加申报2011年1项国家社科基金与1项国家自然科学基金（都不是负责人），不知道是否可以？根据国家社科基金与国家自然科学基金的公告看，好像可以。<br>附，国家社科基金公告有关内容：<br>“十、申报课题的负责人同年度只能申报一个项目。在研国家社科基金和国家自然科学基金各类项目（以结项证书标注日期为准）负责人不能申报新项目。申报国家社科基金项目的负责人同年度不能申报国家自然科学基金或其他国家科技计划项目，其课题组成员也不能作为负责人以内容相同或相近课题申报国家自然科学基金或其他国家科技计划项目。申报单位科研管理部门要认真审核把关，如违规申报，所在单位将被通报批评。”<br>国家自然科学基金公告中无与国家社科基金一起限项的有关内容。<br>另外，是否有一年参加几个月的问题出现？（一年不能超过12个月）<br>谢谢。<apdx></Q>
<A><answer>我觉得，没问题！    打电话给官方机构最保险！</answer><quality>0</quality><upvote>0</upvote><answer>没有问题！</answer><quality>0</quality><upvote>0</upvote></A>
<url>http://muchong.com/t-2855070-1</url>
<Q><title>请教青基经费预算的两个问题</title><apdx>1.青基总金额写25w，可以吗？<br>2.经费预算中，劳务费一定是按15%给出吗？这里的一个贴子（），专家给出的建议是劳务费15%，不能超，也不能四舍五入。可是我的只有12%<apdx></Q>
<A><answer>劳务费不超过15%，听说在15%以下也可以的。</answer><quality>0</quality><upvote>1</upvote><answer>好像今年基金的自主力度提高了，可以写到30W左右呢</answer><quality>0</quality><upvote>1</upvote><answer>劳务费别超过15%就好，而且要注明只能用在学生身上哦！</answer><quality>0</quality><upvote>1</upvote><answer>“谢谢！我写的是“参加项目研究人员的劳务费”，应该可以吧~2011-02-1416:20:52”<br>你还是自己看看规定吧，呵呵，在那个审查表上写的十分清楚！</answer><quality>0</quality><upvote>1</upvote><answer>《2011年度国家自然科学基金项目形式审查明细表》，呵呵！</answer><quality>0</quality><upvote>0</upvote><answer>课题组成员里如果没有学生，就不要写劳务费。</answer><quality>0</quality><upvote>1</upvote><answer>谢谢你们提供的建议：）</answer><quality>0</quality><upvote>0</upvote></A>
<url>http://muchong.com/t-2852303-1</url>
<Q><title>承担科研项目情况和完成自然科学基金项目情况？？</title><apdx>申请书中的承担科研项目情况和和完成自然科学基金项目情况，两部分类容都没有什么要写的，是不是显得太寒蝉啊？大家都是怎么写的?<apdx></Q>
<A><answer>没有就空着呀，难道造假？</answer><quality>0</quality><upvote>1</upvote><answer>2楼正解，没有就不要写</answer><quality>0</quality><upvote>1</upvote><answer>没有就不写啦，额~话说其他成员也没做过什么项目吗？</answer><quality>0</quality><upvote>1</upvote><answer>没有就没有，青年基金不要求的，主要是你的好想法和实验设计。</answer><quality>0</quality><upvote>1</upvote><answer>多谢多谢！</answer><quality>0</quality><upvote>0</upvote><answer>没有就没有，很正常。</answer><quality>0</quality><upvote>1</upvote><answer>没有就不要写</answer><quality>0</quality><upvote>0</upvote><answer>没有就不要写</answer><quality>0</quality><upvote>0</upvote><answer>这里是指基金委的项目吗？</answer><quality>0</quality><upvote>1</upvote><answer>没有空着很正常</answer><quality>0</quality><upvote>0</upvote><answer>顶顶顶顶</answer><quality>0</quality><upvote>0</upvote><answer>实事求是的哦，祝福好运~~~</answer><quality>0</quality><upvote>1</upvote><answer>呵呵，俺也是啥都没有哦</answer><quality>0</quality><upvote>1</upvote><answer>祝福中，呵呵</answer><quality>0</quality><upvote>0</upvote><answer>没有就不写，这不是问题。</answer><quality>0</quality><upvote>1</upvote></A>
<url>http://muchong.com/t-2847021-1</url>
<Q><title>问个青基人员配置问题</title><apdx>本人青椒<br>去年下半年刚进校文章不多<br>请问在人员配置上可以加上学院的同方向的教授不近两年同方向文章很多  去年刚中了面上项目<br>不知道这样会不会让人觉得自己能力不够会因为这点被刷<apdx></Q>
<A><answer>方向相同，但是落脚点可以不同，关键在后面~~~~</answer><quality>0</quality><upvote>1</upvote><answer>教授不超项的话可以</answer><quality>0</quality><upvote>1</upvote><answer>关键是看本子写得如何，祝福楼主</answer><quality>0</quality><upvote>1</upvote><answer>完全可以加个教授，充实团队实力！</answer><quality>0</quality><upvote>1</upvote><answer>教授不是主要的，关于人员的问题，最重要的是构成<br>教授多了相反不好</answer><quality>0</quality><upvote>1</upvote><answer>我的意思  是加一个教授  本来是一个也没有的  呵呵  <br>看大家的意思  加一个教授  是可以接受的<br>我看过别的青基标书也加了研究院  最后也中了  当然人家本来实力就很强</answer><quality>0</quality><upvote>0</upvote><answer>最重要的还是申请者本身实力及本子的水平。加个把教授不是问题。</answer><quality>0</quality><upvote>1</upvote><answer>加不加教授无所谓，关键性是研究生数量</answer><quality>0</quality><upvote>1</upvote><answer>青基最好还是不要加教授比较好，多几个研究生比较实在，最好有个副教授或者两个</answer><quality>0</quality><upvote>1</upvote><answer>关键是专业方向上的投入要明显</answer><quality>0</quality><upvote>1</upvote></A>
<url>http://muchong.com/t-2849454-1</url>
<Q><title>小额资助要写到申请书中么</title><apdx>如题，请教<apdx></Q>
<A><answer>一定要写的-</answer><quality>0</quality><upvote>0</upvote><answer>不用吧，最后由基金委定</answer><quality>0</quality><upvote>1</upvote><answer>只要是国家基金委批的都要写，否者资格审查会被毙掉</answer><quality>0</quality><upvote>1</upvote><answer>小额资助在基金委网站上查不到是否就意味着不算一项基金呢至少分量算不上</answer><quality>0</quality><upvote>0</upvote><answer>同意4楼</answer><quality>0</quality><upvote>0</upvote><answer>好的那就写上吧谢谢大家的忠告建议</answer><quality>0</quality><upvote>0</upvote><answer>这个也要写？似乎听讲座说，基金委决定是否资助还是小额资助，建议搂主还是问问你们学校科技处再决定吧。</answer><quality>0</quality><upvote>1</upvote><answer>这个也要写？似乎听讲座说，基金委决定是否资助还是小额资助，建议搂主还是问问你们学校科技处再决定吧。</answer><quality>0</quality><upvote>0</upvote><answer>LZ是要申请小额资助还是以前承担过小额资助？如果是前者，不需要写出；如果是后者，需要如实填写。</answer><quality>0</quality><upvote>1</upvote><answer>当然要写</answer><quality>0</quality><upvote>0</upvote><answer>正解！！！</answer><quality>0</quality><upvote>0</upvote><answer>对于申请有帮助的，为什么不写呢？</answer><quality>0</quality><upvote>1</upvote></A>
<url>http://muchong.com/t-2854061-1</url>
<Q><title>基金今天终于写完初稿，安慰下自己，不过立项依据不知道是否有点多？</title><apdx>初稿勉强算完成了，立项依据写了3页半，大家觉得字数是不有点多了啊？<apdx></Q>
<A><answer>祝福啊!如果包括参考文献在内就不多啦,单是正文的话是有点不少.</answer><quality>0</quality><upvote>1</upvote><answer>谢了  没算参考文献  个人也觉得比较多，在继续修改中</answer><quality>0</quality><upvote>0</upvote><answer>羡慕呀！</answer><quality>0</quality><upvote>0</upvote><answer>不在文字多少，关键在于创新点够不够！！！祝福楼主！！！</answer><quality>0</quality><upvote>1</upvote><answer>不多，有许多中标的立项依据都在6页左右！</answer><quality>0</quality><upvote>1</upvote><answer></answer><quality>0</quality><upvote>0</upvote><answer>不多，我周围中标的没有少于三页的。</answer><quality>0</quality><upvote>1</upvote><answer>不多，我中的有5业，多多益善</answer><quality>0</quality><upvote>1</upvote><answer>创新点创新点！！！</answer><quality>0</quality><upvote>0</upvote><answer>我立项依据也写了很多，我感觉，只要不是废话，多点也无所谓吧</answer><quality>0</quality><upvote>1</upvote><answer>这怎么能叫多呢？才三页</answer><quality>0</quality><upvote>1</upvote><answer>只要科学、有创意，<br>多少都会得到认可</answer><quality>0</quality><upvote>1</upvote><answer>立项依据也不是多多益善，只要做到阐述结果让人觉得此课题“刻不容缓”且“真实确切”即可，最好能做到简洁...</answer><quality>0</quality><upvote>1</upvote><answer>应该还好吧。我们以前的方式是立项依据就一页（包括参考文献），都是小四字体，1.2倍左右行距。现在扩到2页半左右。</answer><quality>0</quality><upvote>1</upvote><answer>要说字数，页数跟行距字体有关，很难判断你是否写多了</answer><quality>0</quality><upvote>1</upvote><answer>立项依据有项目意义、国内外动态等，规定字数4000-8000，大概在这个范围就可以。我觉得不能说页数，要看字数。<br>个人感觉要说清楚，又不能写太多字，都是忙人，不可能耐心的全部看完。故要在说清楚的前提下，尽量精简。</answer><quality>0</quality><upvote>1</upvote></A>
<url>http://muchong.com/t-2854622-1</url>
<Q><title>关于“承担科研项目情况”</title><apdx>大家在填写的时候怎么填？<br>事无巨细的把所有拿到的基金都列上，还是只写于国基的？<br>谢谢！<apdx></Q>
<A><answer>国基就可以了吧</answer><quality>0</quality><upvote>0</upvote><answer>只写国基。</answer><quality>0</quality><upvote>0</upvote><answer>主持的算不算？<br>记得有次会上，省科技厅的人这样说：<br>“中省自然基金的目的就是：让没有获得国家基金的人推荐给国家基金，如果拿过国基金，一般省基金原则上不再获得！而且一辈子只能拿两次省自然基金”<br>另外，打算申报国青基<br>[]</answer><quality>0</quality><upvote>1</upvote><answer>国基和自己主持的项目</answer><quality>0</quality><upvote>0</upvote><answer>好像专家只关心国基的！</answer><quality>0</quality><upvote>0</upvote><answer>大致明白了，谢谢！</answer><quality>0</quality><upvote>0</upvote></A>
<url>http://muchong.com/t-2853709-1</url>
<Q><title>立项依据中连同参考文献（50篇）约8000字</title><apdx>立项依据中连同参考文献（50篇）约8000字，如何！不知该如何减了?朋友们帮忙看看，这样可以吗？参考文献中49篇英文.感觉国内杂志的文章水平太高的没有几篇，可能我们现在好些的论文都往国外投了。<apdx></Q>
<A><answer>不错！</answer><quality>0</quality><upvote>0</upvote><answer>我觉得参考文献过多，且严重缺少国内的文献，到时候正好遇上本领域专家的话，发现连他的文章都没引，可能会枪毙哦，建议修改添加至少10篇国内期刊论文或著作。</answer><quality>0</quality><upvote>0</upvote><answer>最好写几个国内大牛的文献嘛，以示对大牛的敬礼！</answer><quality>0</quality><upvote>0</upvote><answer>实事求是，有就写没有写啥？不过国内的研究状况一定要清楚，否则就麻烦了</answer><quality>0</quality><upvote>0</upvote><answer>参考文献的格式可以减少不少字</answer><quality>0</quality><upvote>0</upvote><answer>有理。</answer><quality>0</quality><upvote>0</upvote><answer>立项依据的字数是不是严格控制啊？我写了之后，也就三千多，勉强够四千，不知道会不会不合格？<br>借宝地请教问题，呵呵</answer><quality>0</quality><upvote>0</upvote><answer>还是建议增加国内的参考文献，毕竟要国内同行评议的。</answer><quality>0</quality><upvote>0</upvote><answer>国内牛人发的文章都是国外的刊物，发在国内的期刊其实就是一些无关痛痒的文章。---------很正常</answer><quality>0</quality><upvote>0</upvote><answer>自我感觉有点多，25-30比较合适</answer><quality>0</quality><upvote>0</upvote><answer>建议立项依据尽可能浓缩在2~3千字，3千字足够说明你想说的了，没有必要长篇大论堆砌文献进展，切中问题要害就可以了，评审的一般不是小同行，太长的看不下去的，也浪费评审的时间。参考文献也以20~30篇为宜。</answer><quality>0</quality><upvote>0</upvote></A>
<url>http://muchong.com/t-2854012-1</url>
<Q><title>让人头疼的青基申报人资格求教</title><apdx>我和另一位同事（博士、讲师）都打算申报青基，我打算挂上他作为主要参与者（4个月），请问是否符合限项规定？注：他的部分工作与我相关，而且他本人也愿意我挂上他。请大家支招啊，谢谢！<apdx></Q>
<A><answer>当然可以，好好看指南，这个问题就不需要问了吧。中级职称限主持一项，参加无数项。但是也不要太多了。</answer><quality>0</quality><upvote>1</upvote><answer>讲师是可以挂的，不受限项</answer><quality>0</quality><upvote>1</upvote><answer>正解</answer><quality>0</quality><upvote>0</upvote><answer>当心下一年变副高了，就会有问题。</answer><quality>0</quality><upvote>1</upvote><answer>谢谢您！请问您指我或者我的同事变成副高了可能不符合限项吗？但是现在申报2011年的计划应该没有什么问题吧？再次感谢您！</answer><quality>0</quality><upvote>0</upvote><answer>预祝成功</answer><quality>0</quality><upvote>0</upvote><answer>这个不是问题，即使她来年变成副高也不是问题，你看看指南吧。</answer><quality>0</quality><upvote>1</upvote><answer>讲师参与不限项的，只限主持/申请一项。听说升副高以后参与会清零的，不知是否真实，建议电话咨询一下基金委，有答案告诉大家啊。。。</answer><quality>0</quality><upvote>1</upvote></A>
<url>http://muchong.com/t-2850642-1</url>
<Q><title>隐瞒在职研究生身份有严重后果吗？</title><apdx>写个国家自科。<br>是在职，快毕业了。<br>可是要写明白得介绍信，还要解释和博士内容的关系什么的，挺麻烦的。<br>直接不说会怎么样？只说依托单位的工作经历？<br>国家自然科学基金委有全国在读博士的数据库吗？<br>会不会直接审查不通过。<br>补充，不是高级职称。这个推荐信我肯定会开的。<br>[]<apdx></Q>
<A><answer>没有人查这些----------内容好就行。。。</answer><quality>0</quality><upvote>0</upvote><answer>但是没有博士学位申请需要有推荐信吧。</answer><quality>0</quality><upvote>0</upvote><answer>没关系的哦，祝福好运~~~</answer><quality>0</quality><upvote>0</upvote><answer>这是正解，<br>当然若有高级职称也没有问题。</answer><quality>0</quality><upvote>0</upvote><answer>副高以上就什么都ok了</answer><quality>0</quality><upvote>0</upvote><answer>最后不要</answer><quality>0</quality><upvote>0</upvote><answer>不要紧。</answer><quality>0</quality><upvote>0</upvote><answer>应该没事的，不过若有副高以上职称，推荐信也不用了</answer><quality>0</quality><upvote>0</upvote><answer>“不是高级职称。这个推荐信我肯定会开的。”<br>有这个就可以。和博士不博士没关系。<br>是这样的。你说自己是教授，基金委都不会查。但是呢，你中了基金，有人举报，那你就要举证。比如没有获得博士学位的说自己是博士，查的时候，你就要把证书拿出来。</answer><quality>0</quality><upvote>0</upvote><answer>如果你人缘好而且以后不会牛气冲天，没有关系，否则有关系，因为一旦有人举报你，你就惨了，每年基金委都有申明的，那些学校的被撤销，做成处罚。</answer><quality>0</quality><upvote>0</upvote><answer>谢谢，那我还是老实为妙吧。<br>还盼着哪天牛气冲天呢呵呵。<br>咱还是不学唐骏。</answer><quality>0</quality><upvote>0</upvote></A>
<url>http://muchong.com/t-2850871-1</url>
<Q><title>请问2011申请指南中这句话什么意思</title><apdx>见图。是不是说：申请人，也可以参与别的项目呢。<apdx></Q>
<A><answer>只主持一项，可参与，只要名额在限项范围之内</answer><quality>0</quality><upvote>1</upvote><answer>不同类型的可以申请么？呵呵</answer><quality>0</quality><upvote>1</upvote><answer>可以主持一项，可参与若干项(取决于你的职称)，只要名额在限项范围之内就可以。</answer><quality>0</quality><upvote>1</upvote><answer>作为主持者，只能申请一项</answer><quality>0</quality><upvote>0</upvote><answer>你好，我是讲师，可以申请一项和参加一项，都是青基么。</answer><quality>0</quality><upvote>0</upvote><answer>你好，我是讲师，可以申请一项和参加一项，都是青基么。</answer><quality>0</quality><upvote>0</upvote><answer>当然可以。讲师只能主持或（主持）1项，参与不限。</answer><quality>0</quality><upvote>1</upvote></A>
<url>http://muchong.com/t-2854203-1</url>
<Q><title>青基，项目主持人，每年参加项目的时间是10个月好，还是12个月。</title><apdx>青基，项目主持人，每年参加项目的时间是10个月好，还是12个月。<apdx></Q>
<A><answer>8or9就行<br>写多了也没人信</answer><quality>0</quality><upvote>1</upvote><answer>您好：如果我主持一项，还参加一项，时间该怎么写好呢。谢谢你啊。</answer><quality>0</quality><upvote>0</upvote><answer>这样也要加起来12个月吧</answer><quality>0</quality><upvote>1</upvote><answer>主持人最多写10个月，好像没见过一年啥事也不干，只做一个课题的吧</answer><quality>0</quality><upvote>0</upvote><answer>十个月吧，现实点</answer><quality>0</quality><upvote>0</upvote><answer>主持8个月够了。参与4个月</answer><quality>0</quality><upvote>1</upvote><answer>我看到的主持都是写10个月</answer><quality>0</quality><upvote>1</upvote><answer>10个已经够了</answer><quality>0</quality><upvote>0</upvote></A>
<url>http://muchong.com/t-2853406-1</url>
<Q><title>请教国青基申请人简介部分的内容</title><apdx>请问各位达人，申请人简介这部分是否需要把自己以前参加过哪些项目，获得过多少专利等等都要写上？还是只写发表的论文和论著？谢谢。<apdx></Q>
<A><answer>自己的都可以写</answer><quality>0</quality><upvote>0</upvote><answer>应该是随便吧，我个人感觉！！！</answer><quality>0</quality><upvote>0</upvote></A>
<url>http://muchong.com/t-2854444-1</url>
<Q><title>青年基金申请书中申请人简介</title><apdx>请问下大家，青年基金申请书中“申请人简介”需要将其他主要成员简介也一起写进去吗？因为大纲里都只是说“申请人的学历和研究工作简历....”，没说“主要成员...”。我感觉没必要加进去。大家是怎么写的呀？<apdx></Q>
<A><answer>前面有帖子讨论貌似最好是写一两个最主要的成员，如果可以的话就写一个吧，肯定比不写好啊</answer><quality>0</quality><upvote>0</upvote><answer>如果有就写，也可只写负责人的简历。</answer><quality>0</quality><upvote>0</upvote><answer>我看了几个青基的，都只写了PI的简历，面上的没看不知道</answer><quality>0</quality><upvote>0</upvote><answer>可写主持人和第一参与人。</answer><quality>0</quality><upvote>0</upvote><answer>同意楼上的</answer><quality>0</quality><upvote>0</upvote><answer>我的只写了自己，不用写其他人。</answer><quality>0</quality><upvote>1</upvote></A>
<url>http://muchong.com/t-2853920-1</url>
<Q><title>申请的项目与在研项目的关系请教</title><apdx>两种是关系紧密好？还是不同的方向好一些？<br>请各位指教！谢谢<apdx></Q>
<A><answer>最好紧密一些。说明有前期工作基础-------</answer><quality>0</quality><upvote>1</upvote><answer>紧密些好，但又要有深入的方面</answer><quality>0</quality><upvote>1</upvote><answer>如果是结题的话，肯定是有联系的好啊！如果是在研的话，关系不大才好吧！</answer><quality>0</quality><upvote>1</upvote><answer>问题不大</answer><quality>0</quality><upvote>0</upvote><answer>没有结题</answer><quality>0</quality><upvote>0</upvote><answer>关系不大为好</answer><quality>0</quality><upvote>0</upvote><answer>关系紧密好</answer><quality>0</quality><upvote>0</upvote><answer>紧密些的好</answer><quality>0</quality><upvote>0</upvote><answer>要有联系</answer><quality>0</quality><upvote>0</upvote><answer>有区别也有联系。</answer><quality>0</quality><upvote>0</upvote><answer>对，最好是有一定联系又是不同的研究内容。否则一般不会重复资助类似的内容的。</answer><quality>0</quality><upvote>1</upvote><answer>还是紧密一些好，但也要有些发展</answer><quality>0</quality><upvote>1</upvote><answer>紧密好啊，这样一看基础雄厚</answer><quality>0</quality><upvote>1</upvote><answer>有联系，但创新点大大不同。</answer><quality>0</quality><upvote>1</upvote><answer>可以有</answer><quality>0</quality><upvote>0</upvote><answer>应该属于同一学科吧</answer><quality>0</quality><upvote>1</upvote></A>
<url>http://muchong.com/t-2853139-1</url>
<Q><title>液晶中相位光栅的课题应报数理学科还是信息学科部</title><apdx>液晶中相位光栅的课题应报数理学科还是信息学科部，信息科学部有非线性光学材料；数理学科有非线性光学，但我倾向报信息科学部。犯难，好像数理学科2010资助比例大，<apdx></Q>
<A><answer>还是数理好，信息的不好中</answer><quality>0</quality><upvote>1</upvote></A>
<url>http://muchong.com/t-2854023-1</url>
<Q><title>2011理论物理专款拨款了没有？</title><apdx>始终都是“未拨款”状态，原来说12月份的。都这样吗？<br>谢谢！<apdx></Q>
<A><answer>可问问科研处。</answer><quality>0</quality><upvote>0</upvote></A>
<url>http://muchong.com/t-2853843-1</url>
<Q><title>请问青年基金的项目主持人是不能在参加同年申请的另外一个青年项目了么</title><apdx>请问青年基金的项目主持人是不能在参加同年申请的另外一个青年项目了么？<apdx></Q>
<A><answer>也想知道这个问题</answer><quality>0</quality><upvote>0</upvote><answer>知不知道，青基的项目参加人有没有年龄要求。</answer><quality>0</quality><upvote>0</upvote><answer>如果是中级无所谓吧，高级的有3项限项吧</answer><quality>0</quality><upvote>1</upvote><answer>中级职称的不限，年龄只是限定项目主持人的，男35女40，参与者不限年龄的</answer><quality>0</quality><upvote>1</upvote></A>
<url>http://muchong.com/t-2854140-1</url>
<Q><title>[关贴]请大家帮我的青基队伍提提意见（内容有添加）</title><apdx>我来自某地方师范高校，题目和医学图像有关。队伍如下：<br>我（副高）+1教授+2讲师+1实验师+1放射科副主任医师+2硕士生。<br>大家帮忙提提意见，这个队伍合理吗？<br>还有，在成员中的排列顺序是否一定得按照职称高低排列。<br>多谢了。<br>[]<apdx></Q>
<A><answer>非常全了~~~我认为不错</answer><quality>0</quality><upvote>1</upvote><answer>这么多人啊</answer><quality>0</quality><upvote>0</upvote><answer>教授貌似有点问题，听说青年项目最好不要有正高职称的</answer><quality>0</quality><upvote>1</upvote><answer>教授和我的方向联系很密切，而且在合作。</answer><quality>0</quality><upvote>0</upvote></A>
<url>http://muchong.com/t-2853598-1</url>
<Q><title>请问，青年基金要加一个副高或者正高的参与人么？</title><apdx>有没有什么特殊的说法？加了一定有增色，还是说反而让人质疑申请人的能力，抑或让人反感，有故意之嫌。<apdx></Q>
<A><answer>一般都会加的</answer><quality>0</quality><upvote>0</upvote><answer>正高不要加，加副高。</answer><quality>0</quality><upvote>0</upvote></A>
<url>http://muchong.com/t-2854024-1</url>
<Q><title>关于在职博士研究生申请国家自然基金的问题，请明白人回答，谢谢！</title><apdx>请问在职博士研究生，是既需要两个高级推荐信还需要导师的同意函，还是只需要导师的同意函？<apdx></Q>
<A><answer>如果你已经有高级职称了，现在正在在职读博士的话，那么只需要导师的同意函，如果没有高级职称的话，那么两者都要。</answer><quality>0</quality><upvote>1</upvote><answer>多谢！！</answer><quality>0</quality><upvote>0</upvote></A>
<url>http://muchong.com/t-2854069-1</url>
<Q><title>关于承担科研项目情况</title><apdx>读博期间，曾经参加导师的项目，位次很靠后，要写在青基申请书中吗？<apdx></Q>
<A><answer>不要写，没用。</answer><quality>0</quality><upvote>0</upvote></A>
<url>http://muchong.com/t-2854047-1</url>
<Q><title>询问：这样的标书是否一点希望都没了？</title><apdx>刚博士毕业没有经费，逼上梁山了，也想试试青基金，我自认为选题和标书写得还可以，有几篇相关英文文章。于是，找了一位以前课题组的老师看了一下（曾中过两项国基），得出如此评语。<br>  你的申报材料我看了，坦白地说获得资助的可能性基本上没有，我认为：<br>1.选题的新颖性、理论性很前瞻性不突出；<br>2.研究内容不属于基础理论范畴，侧重在应用，一般这样的题目基金不支持；<br>3.前言的内容简单，没有阐述清楚研究的目的和意义，现状分析的jiao简单，尽量写到8000字左右；<br>4.研究内容和方法简单，内容上没有特别突出的创新性，这部分是材料的核心部分，应该仔细地写，关键是抓住问题的核心点；<br>5.整个材料的组织不是很严谨的。<br>  非常失望和沮丧，对青金一下子没了热情。想请前辈们指点，我该何处何从？  <br>  我不想放弃青年基金，在普通高校，没有经费，什么科研都开展不开来。唉。。。。<br>[]<apdx></Q>
<A><answer>慢慢来吧。也不能着急</answer><quality>0</quality><upvote>0</upvote><answer>有大牛给你斧正，真幸福啊。<br>楼主最好根据大牛给你的建议一一指正。</answer><quality>0</quality><upvote>1</upvote><answer>3.前言的内容简单，没有阐述清楚研究的目的和意义，现状分析的叫简单，尽量写到8000字左右；<br>错别字一个：叫改为较</answer><quality>0</quality><upvote>0</upvote><answer>继续啊！加油！！共勉！</answer><quality>0</quality><upvote>0</upvote></A>
<url>http://muchong.com/t-2853955-1</url>
<Q><title>基金题目的字数有要求没有</title><apdx>基金题目的字数有要求没有<apdx></Q>
<A><answer>有啊，你打开申请书填写时他会提示你题目是多少字以内。我记得去年是50字以内（记得不很清楚了）。</answer><quality>0</quality><upvote>1</upvote><answer>听说最好控制在25个字内</answer><quality>0</quality><upvote>1</upvote></A>
<url>http://muchong.com/t-2853874-1</url>
<Q><title>青年基金的题目字数要求</title><apdx>各位基友，弱弱的问一下，青年基金的题字数有什么要求没？我的题目数了一下有28个字，感觉有点长。<apdx></Q>
<A><answer>简单明了，能吸引眼球。最好25个字以内</answer><quality>0</quality><upvote>1</upvote></A>
<url>http://muchong.com/t-2853778-1</url>
<Q><title>今年新增加：通过计算机软件对申请书内容进行比对，到底查到什么程度</title><apdx>今年俺要同时申请两个类型的项目，<br>如果主题完全不一样，但属于同一领域。文献综述里有700字左右内容重复，这算——<br>“将内容相同或相近的项目，向同一科学部或不同科学部申请不同类型项目的资助”<br>吗？<apdx></Q>
<A><answer>个人觉得算。<br>求官方论证。</answer><quality>0</quality><upvote>1</upvote><answer>标书最好还是不要抄的为好。。。自己写。。。。。。</answer><quality>0</quality><upvote>0</upvote></A>
<url>http://muchong.com/t-2853427-1</url>
<Q><title>申请国基和博士点基金的创新点有部分重复，会不会造成严重后果？</title><apdx>申请国基和博士点基金的创新点有部分重复，国内同一学科和研究方向的圈子不大，如果两份申请书凑巧被送到同一评审专家手里，会不会造成严重后果？<br>[]<apdx></Q>
<A><answer>这样的几率非常小。<br>而且专家也不会记得你以前申过啥。</answer><quality>0</quality><upvote>0</upvote><answer>同问这个问题</answer><quality>0</quality><upvote>0</upvote><answer>应该没什么问题，如果专家心理没问题的话，不会介意多申报课题，毕竟都是从那个阶段走过来的，只要创意足够好，大可放心</answer><quality>0</quality><upvote>1</upvote></A>
<url>http://muchong.com/t-2853445-1</url>
<Q><title>请教一个基金限项的问题</title><apdx>去年有人申请面上，中了，挂了我的，去年中级。<br>但是今年评上副高了，自己想主持申请，另外有两个人挂我的话，超项吗？<br>谢谢大家了<apdx></Q>
<A><answer>不要让另外两个人挂你的名就可以了-----</answer><quality>0</quality><upvote>1</upvote><answer>似乎是超了</answer><quality>0</quality><upvote>0</upvote><answer>超~~~</answer><quality>0</quality><upvote>0</upvote><answer>新规定应该不超吧，高级职称主持或作为主要参与人的，不超过3个，但是要控制一年工作时间不要超过12个月</answer><quality>0</quality><upvote>1</upvote><answer>超了</answer><quality>0</quality><upvote>0</upvote><answer>申请课题，小心谨慎。</answer><quality>0</quality><upvote>0</upvote><answer>好像超了哦，祝福好运~~~</answer><quality>0</quality><upvote>1</upvote><answer>竟然如此纠结~~</answer><quality>0</quality><upvote>0</upvote><answer>你中级职称时候的参与项目不纳入限项数目，因此今年你自己可以申请，另外再让人家挂2个</answer><quality>0</quality><upvote>1</upvote><answer>正解</answer><quality>0</quality><upvote>0</upvote><answer>超，你只能参加3项，去年一项，今年你自己一项，别人只能再挂你一个了</answer><quality>0</quality><upvote>1</upvote><answer>不超，放心吧！不过今年还是不让别人挂的好，要是都中了，嘿嘿，你以后怎么办？</answer><quality>0</quality><upvote>1</upvote></A>
<url>http://muchong.com/t-2852697-1</url>
<Q><title>聘请的外籍华人教授能否申请国家基金</title><apdx>聘请的美籍华人教授作为单位客座研究员（岁数已超过40），能否申请国家自然科学基金？谢谢回答！<apdx></Q>
<A><answer>能用中文写申请吗？</answer><quality>0</quality><upvote>0</upvote><answer>可以用中文，美籍华人。</answer><quality>0</quality><upvote>0</upvote><answer>是否只能申请国际合作项目，不能申请面上等项目。</answer><quality>0</quality><upvote>0</upvote></A>
<url>http://muchong.com/t-2853461-1</url>
<Q><title>管理科学与工程，青年基金，大家看看这部分预算都是0可以么，如果不行怎么填写。</title><apdx>管理学部，青年基金，大家看看这部分预算都是0可以么，如果不行怎么填写。<apdx></Q>
<A><answer>需要购买笔记本电脑等，也需要网线，u盘，墨盒吧</answer><quality>0</quality><upvote>1</upvote><answer>不是说写上购买笔记本电脑不好么，如果写放到那部分呢。</answer><quality>0</quality><upvote>0</upvote><answer>谁说不好？</answer><quality>0</quality><upvote>0</upvote></A>
<url>http://muchong.com/t-2853312-1</url>
<Q><title>参考文献最好不要出现书？</title><apdx>听一位老基金人说，参考文献中最好不要用书，要用论文。请大家讨论一下，为什么？<apdx></Q>
<A><answer>论文成果比较新</answer><quality>0</quality><upvote>0</upvote><answer>呵呵，很逗呢，外文书籍中的某个章节既是某个专题，写的很好很到位，难道你不用！</answer><quality>0</quality><upvote>0</upvote><answer>没有这么一说，不过我用的一般都是最近5年的论文，极个别非常经典的除外。</answer><quality>0</quality><upvote>1</upvote><answer>导师跟我说过，但有时确实用到了，不引又不是。。</answer><quality>0</quality><upvote>1</upvote><answer>感觉没必要较真，该引则引。</answer><quality>0</quality><upvote>1</upvote></A>
<url>http://muchong.com/t-2852376-1</url>
<Q><title>请教青基队伍和有关承担科研项目情况</title><apdx>两个问题：<br>1.青基申请书中关于承担科研项目情况：目前本人只有个学校的小基金，3万，需不需要些入？<br>2.团队成员问题：目前实在找不到其他人员，我是负责人，只能找4个硕士生。问题是这样的队伍感觉是不是太弱了？还有硕士生的话需不需要在申请人简介中一一介绍？<br>非常感谢<apdx></Q>
<A><answer>1可以考虑写上<br>2课题组太小了，难道讲师、助教都找不到了</answer><quality>0</quality><upvote>0</upvote><answer>助理工程师可以写入吗？</answer><quality>0</quality><upvote>0</upvote><answer>1.要写上的话，你就要明确说出你承担的校基金和申请的国基的联系与差别——没联系的话，就没必要写了吧；反之，如果没有本质差别的话，你写上了，不是让别人说你重复申请经费吗，呵呵。所以，这个我个人还是建议楼主慎重啊，不写还省点事呢<br>2.不知楼主是何专业，从你们学校的实验室，再拉一个工程师、技师等（比如主管测试分析），如果再能加一个博士生，那就是很好的团队了</answer><quality>0</quality><upvote>0</upvote><answer>学校的基金就不要写了,没有档次啊,至少的省部的<br>人数是少点,我的也不多啊</answer><quality>0</quality><upvote>0</upvote><answer>1、不是自然基金就别写了。<br>2、再找些讲师或博士吧。</answer><quality>0</quality><upvote>0</upvote><answer>如果校基金做的那个相当的好，有突出的发现和奖励贡献可以写，以示你的能力水平；<br>团队的确弱了些，不管怎样，拉几个实验师、讲师之类的也可以么？</answer><quality>0</quality><upvote>0</upvote><answer>学校的基金就不要写了</answer><quality>0</quality><upvote>0</upvote><answer>青年基金项目组以35岁以下的青年研究人员组成！你的项目组成员还需要补充讲师和博士生2～3名！</answer><quality>0</quality><upvote>1</upvote><answer>如果你没主持过国家或省部级项目，建议将你的校基金写入，否则评审专家会认为你的研究基础过于薄弱!</answer><quality>0</quality><upvote>0</upvote><answer>谢谢，另外，项目组成员一定都要35岁以下吗？</answer><quality>0</quality><upvote>0</upvote><answer>哎，有人说写，有人说不写，不知道听哪个的好呢？</answer><quality>0</quality><upvote>1</upvote></A>
<url>http://muchong.com/t-2828800-1</url>
<Q><title>申请书提纲括号内的字能不能删掉</title><apdx>（研究意义、国内外研究现状及发展动态分析，需结合科学研究发展趋势来论述科学意义；或结合国民经济和社会发展中迫切需要解决的关键科技问题来论述其应用前景。附主要参考文献目录）<br>这些字要不要删掉<apdx></Q>
<A><answer>自己顶一下</answer><quality>0</quality><upvote>0</upvote><answer></answer><quality>0</quality><upvote>0</upvote><answer>据专家讲，最好别删。删了也没问题，我就删了，中了。不在这些形式问题上，关键是内容。</answer><quality>0</quality><upvote>1</upvote><answer>可以删掉的，但要在确认内容基本按括号内的思路阐述之后...</answer><quality>0</quality><upvote>0</upvote><answer>不可以，好像指南里有明确规定。删掉会认为你不符合格式。放在那呗，也不影响啥</answer><quality>0</quality><upvote>1</upvote><answer>最好不要删</answer><quality>0</quality><upvote>0</upvote><answer>好像今年又特别规定不删呢，楼主看看红体字部分的内容吧<br>！</answer><quality>0</quality><upvote>1</upvote><answer>jjw纠结的规定</answer><quality>0</quality><upvote>0</upvote><answer>放在那里感觉怪怪的</answer><quality>0</quality><upvote>0</upvote><answer>千万别删哦,不然初筛就会出局.</answer><quality>0</quality><upvote>1</upvote><answer>括弧的可以删除吧</answer><quality>0</quality><upvote>0</upvote><answer>到底能不能删啊</answer><quality>0</quality><upvote>0</upvote><answer>我看到我老师的中标书删除了。说的是括弧里面的</answer><quality>0</quality><upvote>1</upvote><answer>既明确规定不能删，为何要顶风上？</answer><quality>0</quality><upvote>1</upvote><answer>在报告正文前的红色字体里，有要求不删，<br>我认为还是最好别删吧</answer><quality>0</quality><upvote>1</upvote><answer>同问~~<br>感觉放在那里怪怪的，难道是最后提醒评审专家的？<br>赫赫</answer><quality>0</quality><upvote>0</upvote><answer>绝对可以删掉！我以前的基金申请书都是删掉的。其实删不删对您的申请没有影响。<br>如果没有删掉的话，就像是新衣服没有剪标签一样！</answer><quality>0</quality><upvote>1</upvote><answer>我也感觉放在那里怪怪的，还有那些可恶的红字，很影响整体美观，但就是不敢删，万一影响初审就残了</answer><quality>0</quality><upvote>0</upvote><answer>把自己要添的内容添加进去就可以了啊，最好不要乱删！</answer><quality>0</quality><upvote>1</upvote><answer>以前都删掉，但今年有红色字体标注在那里，难道楼主没看到，删掉就不符合标准了，何必去多此一举。</answer><quality>0</quality><upvote>0</upvote></A>
<url>http://muchong.com/t-2848570-1</url>
<Q><title>急！我的国基WORD文档打开时怎么不出现安全警告了，没法启用宏了</title><apdx>求助各位虫虫：我的国基WORD文档打开时怎么不出现安全警告了，没法启用宏了，我想修改基金的标题部分，点不开自动出现的框框了？怎么恢复？<apdx></Q>
<A><answer>舍得的话，重装系统，重装Word，总比你反复试验，着急得不得了好！</answer><quality>0</quality><upvote>0</upvote><answer>不用急，都在设置里呢<br>工具-选项。安全吧。<br>找到那个宏的选项。<br>启用即可。</answer><quality>0</quality><upvote>1</upvote></A>
<url>http://muchong.com/t-2852159-1</url>
<Q><title>拟采取的研究方案及可行性分析的写作框架</title><apdx>研究方法按照研究内容逐一给出，但发现实验部分与实验手段与方法重合了，关键技术部分也是与方法部分重。大家都是如何写这部分的，给点建议吧，修改的乱了都。<apdx></Q>
<A><answer>一个内容两个角度写，<br>内涵有重复，语言无重复。</answer><quality>0</quality><upvote>2</upvote><answer>呵呵，这里真的不好掌握！</answer><quality>0</quality><upvote>1</upvote><answer>我也感觉类似问题不知怎么处理？</answer><quality>0</quality><upvote>1</upvote><answer>关注。。。</answer><quality>0</quality><upvote>0</upvote><answer>深有同感，帮顶</answer><quality>0</quality><upvote>0</upvote><answer>需要好好想想怎么区分侧重点！</answer><quality>0</quality><upvote>1</upvote><answer>一个是做什么，一个是怎么做，要注意区分！内容和我侧重点肯定不能一样，否则就乱且没有条理！！！</answer><quality>0</quality><upvote>1</upvote><answer>分清侧重点</answer><quality>0</quality><upvote>0</upvote><answer>赞同</answer><quality>0</quality><upvote>0</upvote><answer>内涵有重复，语言无重复。</answer><quality>0</quality><upvote>1</upvote><answer>这部分是不太好写</answer><quality>0</quality><upvote>1</upvote><answer>一个是做什么，一个是怎么做，要注意区分！内容和我侧重点肯定不能一样，否则就乱且没有条理！！！这个比较正统</answer><quality>0</quality><upvote>1</upvote><answer>的确有重复的，不过每一部分的侧重点不同，也可以将类似内容换不同的说法。</answer><quality>0</quality><upvote>1</upvote><answer>我觉得两方面有相同点是可以的，但是一个注重方法，一个注重实际的实验步骤，这个应该是对的。</answer><quality>0</quality><upvote>1</upvote><answer>9楼很犀利，学习下<br>[]</answer><quality>0</quality><upvote>1</upvote><answer>注意语句上的把握</answer><quality>0</quality><upvote>1</upvote><answer>技术相对简单一些，方法详细一些</answer><quality>0</quality><upvote>0</upvote><answer>学习了，我也是很纠结</answer><quality>0</quality><upvote>1</upvote><answer>的确不好弄，很迷糊的东西！<br>多看看基金申请书，参考一下，会好些！</answer><quality>0</quality><upvote>0</upvote></A>
<url>http://muchong.com/t-2852045-1</url>
<Q><title>参考文献有没有规定的格式？</title><apdx>还是自己随意组织？<apdx></Q>
<A><answer>按照国际标准格式写。</answer><quality>0</quality><upvote>0</upvote><answer>统一就好，看了很多申请书，各不相同！</answer><quality>0</quality><upvote>1</upvote></A>
<url>http://muchong.com/t-2852032-1</url>
<Q><title>基金摘要的下标没法设有什么办法？</title><apdx>基金摘要的下标没法设有什么办法？如CO2<apdx></Q>
<A><answer>CO2就这样也可以的</answer><quality>0</quality><upvote>0</upvote><answer>可以可以</answer><quality>0</quality><upvote>0</upvote></A>
<url>http://muchong.com/t-2851294-1</url>
<Q><title>今年面上项目写几项研究内容</title><apdx>请问各位，我原来一般写三项研究内容。<br>今年面上项目改成四年了，写几项研究内容比较合适呢？谢谢！<apdx></Q>
<A><answer>帮助顶下，同问。</answer><quality>0</quality><upvote>0</upvote><answer>我写了6项，是不是太多了。</answer><quality>0</quality><upvote>1</upvote><answer>估计有点多，年限的延长是为了出好成果，避免着急结题！<br>因此不宜过多，3~4个足矣！</answer><quality>0</quality><upvote>1</upvote><answer>保险起见还是按照以前的写。也没有要求有所改变</answer><quality>0</quality><upvote>1</upvote></A>
<url>http://muchong.com/t-2853012-1</url>
<Q><title>30篇英文参考文献占了5000字符，怎么处理参考文献呢。</title><apdx>30篇英文参考文献占了5000字符，而立项依据与研究内容要求（4000-8000字），怎么处理参考文献呢。<apdx></Q>
<A><answer>参考文献应该不算在内</answer><quality>0</quality><upvote>0</upvote><answer>不要太在乎字数，自己觉得说清楚就行！<br>能用一条一条摆出来的就一条一条摆出来，给人一目了然就行。不能都是大段大段的，让别人评审起来头痛的！<br>面上写个30页，青基25页很正常的</answer><quality>0</quality><upvote>1</upvote><answer>参考文献可以适当缩到20篇，但是应该尽量留下最新的、刊物级别比较高的，当然国内同领域的大牛论文也应适当考虑。</answer><quality>0</quality><upvote>2</upvote><answer>删一些呗，我是这样弄的，比如写论文的时候支持某一点论述的可以引四五篇的，基金申请里就引一两篇，选期刊最牛或文章最新或被引用最多行内人都知道的</answer><quality>0</quality><upvote>1</upvote><answer>写那么多干吗人家又不看</answer><quality>0</quality><upvote>1</upvote><answer>没啥，我的50个参考文献</answer><quality>0</quality><upvote>0</upvote><answer>参考文献不算字数。</answer><quality>0</quality><upvote>0</upvote></A>
<url>http://muchong.com/t-2851344-1</url>
<Q><title>关于青年基金超项的疑问？</title><apdx>我是刚进高校工作的博士生，以前学校的博士副导师申请面上项目想让我挂名。<br>我想请教各位大大，<br>1，如果挂了名，那我今年还能以自己的名义申请青年基金吗？<br>2，申请的青年基金可以和导师项目的研究方向接近么？<br>非常感谢各位~~<apdx></Q>
<A><answer>1,当然可以，限项3项；<br>2，一个青基一个面上，只要你写得能说服reviewer，我祝福你！</answer><quality>0</quality><upvote>1</upvote><answer>1、可以刮，中级职称挂多少项都无所谓，但你只能主持1项，今年可以申请青年基金（作为主持人）<br>2、方向可以接近，但影响命中率</answer><quality>0</quality><upvote>1</upvote></A>
<url>http://muchong.com/t-2852858-1</url>
<Q><title>请问，申请青年基金的时候会出现纸质版和电子的版号不一样的情况吗？</title><apdx>请问，申请青年基金的时候会出现纸质版和电子的版号不一样的情况吗？啥时候回出现呀？<br>另外，最后一页签名页上，打印出来后，不会出现版号吧？<br>我想先把最后一页打印出来签上字，担心后续电子版有修改，导致版本号不一样，会出现这个问题吗？<br>谢谢~~<apdx></Q>
<A><answer>但是打出来你就不能改变题目了</answer><quality>0</quality><upvote>1</upvote><answer>最后一页签名页上不出现版号。</answer><quality>0</quality><upvote>1</upvote><answer>谢谢楼上两位虫虫</answer><quality>0</quality><upvote>0</upvote></A>
<url>http://muchong.com/t-2851676-1</url>
<Q><title>中48批博后基金的在职博后，请问还能申请教育部新教师吗？</title><apdx>如题，多谢<apdx></Q>
<A><answer>出站后在教育部门工作才能申请教师资格------------</answer><quality>0</quality><upvote>1</upvote><answer>我是工作以后，在工作单位做的博士后，教师资格是有的。不知道博后基金在这里算不算是国家项目？</answer><quality>0</quality><upvote>0</upvote><answer>应该算的---</answer><quality>0</quality><upvote>0</upvote><answer>教育部博士点基金只能算是省部级课题!</answer><quality>0</quality><upvote>1</upvote></A>
<url>http://muchong.com/t-2851218-1</url>
<Q><title>青年基金的标题需要比较详细吗？</title><apdx>是不是比较general的标题让人觉得很大很宽？<apdx></Q>
<A><answer>一定要具体点  直接说明内容</answer><quality>0</quality><upvote>1</upvote></A>
<url>http://muchong.com/t-2852561-1</url>
<Q><title>谁知道广东省自然科学基金什么时候开始申请</title><apdx>有知道的虫子麻烦说一下。<apdx></Q>
<A><answer>印象中是每年的3月底吧</answer><quality>0</quality><upvote>1</upvote><answer>我也想知道博士启动何时申报呢</answer><quality>0</quality><upvote>1</upvote></A>
<url>http://muchong.com/t-2852226-1</url>
<Q><title>改基金改到什么时候算理想状态了</title><apdx>每次看，都改动点。什么情况是至善了？有标准么？。。看多了，真有点要吐了。<apdx></Q>
<A><answer>最难的是，自己没有太大把握确定改过的都比不改的好。</answer><quality>0</quality><upvote>0</upvote><answer>改到评审人没有任何理由说NO时止，最好是找成功申请过的人帮你改改，自己看会存在盲区的...</answer><quality>0</quality><upvote>1</upvote><answer>谢谢指导，社科的，过几天就交了，都在度假中，只能自己孤军奋战了。不过实在有点厌倦了，早点交完也好，早解放。就像前面一个老师说的，现在真的像坐牢。</answer><quality>0</quality><upvote>0</upvote><answer>放几天后再改</answer><quality>0</quality><upvote>0</upvote><answer>改到自己都不想干了就差不多了</answer><quality>0</quality><upvote>1</upvote><answer>改到自己看到就吐</answer><quality>0</quality><upvote>0</upvote><answer>我还没有写</answer><quality>0</quality><upvote>0</upvote><answer>同感！我都木了</answer><quality>0</quality><upvote>0</upvote><answer>我都快吐了！</answer><quality>0</quality><upvote>0</upvote><answer>据说要改到增一字则多，删一字则少的地步，如宋玉描述的东家之子的状态就可以了</answer><quality>0</quality><upvote>1</upvote><answer>很苦恼，改是永远无止境的</answer><quality>0</quality><upvote>0</upvote></A>
<url>http://muchong.com/t-2844691-1</url>
<Q><title>青年基金申请课题与以往研究方向以及老板的专业方向都相去甚远，怎么写才有可能中？</title><apdx>青年基金申请课题与以往研究方向以及老板的专业方向都相去甚远，怎么写才有可能中？是不是希望很渺茫？以往发表的文章都与申请方向无关，只是目前有一个省基金支持，所以有些许工作基础，省基金支持到2011年底就结束，目前青基申请的课题与省基金支持的还是有些差异，不知道会不会影响青基的申请，在承担科研项目这一栏要不要写上呢？<apdx></Q>
<A><answer>哎！这世道谁能说清楚呢？<br>申请指南上和青年基金评议要点上<br>都说明青年基金不要过分注重研究基础<br>但是我的本子上人家就说我研究基础差</answer><quality>0</quality><upvote>2</upvote><answer>就是依据已发表的论文，判断研究基础差？哎，难怪我毕业的时候有老师再三跟我强调，找工作最好不要改行，不然博士期间的研究基础浪费了，基金也不好申请。</answer><quality>0</quality><upvote>0</upvote></A>
<url>http://muchong.com/t-2849858-1</url>
<Q><title>青基中，关于字数与字符数的问题。</title><apdx>申请书中要求，立项依据与研究内容要求（4000-8000字），是指WORD-工具中-字数统计    中的字数还是字符数呢。<apdx></Q>
<A><answer>就算超过也没关系的，不要太拘泥于字数，能把意思说清楚就行了<br>但要注意，本子内容一定要有保证，否则太长或太短都会引起评阅人的不快！</answer><quality>0</quality><upvote>1</upvote><answer>说到这顺便问一下，参考文献算不算在字数内呢？<br>麻烦知情的说下，谢谢！</answer><quality>0</quality><upvote>2</upvote><answer>我也犯愁啊！<br>（一）立项依据与研究内容这一项要求4000-8000字，而该项目下有5个部分，我光第一个部分（立项依据，包括立项动机、研究现状分析与参考文献）就快8000字数了。怎么办？<br>字数会不会作为初删的依据？</answer><quality>0</quality><upvote>2</upvote></A>
<url>http://muchong.com/t-2851352-1</url>
<Q><title>论文发表数是不是对青基申请有重要影响？</title><apdx>本人偏工程，SCI2篇，EI6篇，是不是会让评委觉得研究基础不好？<apdx></Q>
<A><answer>基础不错</answer><quality>0</quality><upvote>0</upvote><answer>研究基础还可以，关键看本子的质量！</answer><quality>0</quality><upvote>1</upvote><answer>比我强，我只有一篇通迅作者的SCI，3篇EI，也偏工程，哎，弱呀</answer><quality>0</quality><upvote>1</upvote><answer>加油！祝福楼主申请成功</answer><quality>0</quality><upvote>0</upvote><answer>楼主的研究基础已经不错了，青基对前期工作的要求没有那么高，祝福楼主</answer><quality>0</quality><upvote>2</upvote><answer>已经很不错了  应该没有问题当然申请的项目要好</answer><quality>0</quality><upvote>2</upvote><answer>已经不错了</answer><quality>0</quality><upvote>0</upvote><answer>基础已经很好了，祝福楼主高中！</answer><quality>0</quality><upvote>1</upvote><answer>非常不错的基础啊！</answer><quality>0</quality><upvote>0</upvote><answer>如果论文与申请课题相关、甚至是前期工作，那么研究基础很不错了，关键看本子的质量</answer><quality>0</quality><upvote>1</upvote><answer>路过，学习中！！</answer><quality>0</quality><upvote>0</upvote><answer>青基的要求不高的</answer><quality>0</quality><upvote>0</upvote></A>
<url>http://muchong.com/t-2849020-1</url>
<Q><title>请问：以在职博士申请，导师写推荐信，导师能当参加人吗？</title><apdx>请问：以在职博士申请，导师写推荐信，导师能当参加人吗？<apdx></Q>
<A><answer>貌似不符合逻辑，没有人给自己写推荐信</answer><quality>0</quality><upvote>1</upvote></A>
<url>http://muchong.com/t-2851946-1</url>
<Q><title>请问大家研究生的劳务费每人每年是多少？</title><apdx>请问大家研究生的劳务费每人每年是多少？<apdx></Q>
<A><answer>500元/月人</answer><quality>0</quality><upvote>0</upvote><answer>400元/越</answer><quality>0</quality><upvote>0</upvote><answer>根据工作成果定200-2000不等</answer><quality>0</quality><upvote>1</upvote><answer>根据工作成果定200-2000每月不等</answer><quality>0</quality><upvote>0</upvote><answer>300/月</answer><quality>0</quality><upvote>0</upvote><answer>我一分没得有  跟了老板整整五年</answer><quality>0</quality><upvote>0</upvote><answer>没有钱啊<br>哈哈</answer><quality>0</quality><upvote>0</upvote></A>
<url>http://muchong.com/t-2851771-1</url>
<Q><title>青年基金申请关于创新性的疑问</title><apdx>到底要多么新呢？我很纠结<br>年前有个想法，做了一定量的文献检索后，动笔写，随着不断深入，基本完成。竟然发现国外有篇文献与我的思想很相似，导致现在我的思想大受干扰。我一怒之下，继续检索文献，我想表达的这种思想也就这篇文献有，真无语。<br>请教各位虫友，难道大家申请的课题一定是国内外的人从来没做过的，没见到过的么？如果评审人有查看参考文献的习惯，会发现这种思想上的近似（我也曾经审过基金，就仔细阅读过引文）。遇到这种问题如何处理，大家帮我想想办法，多谢各位<apdx></Q>
<A><answer>也许评审人发现不了，但一旦被发现，肯定是毙掉！<br>还是建议多下点功夫考虑下与那篇文献的区别。</answer><quality>0</quality><upvote>0</upvote></A>
<url>http://muchong.com/t-2851842-1</url>
<Q><title>申请人简介问题</title><apdx>今年的申请人的研究工作简历还需要从本科阶段填起吗？还是直接从硕士或博士阶段开始就可以？简介中需要介绍曾经和现承担或参与的课题情况吗？谢谢<apdx></Q>
<A><answer>没有人帮我解疑答惑吗？？？？？？？</answer><quality>0</quality><upvote>0</upvote></A>
<url>http://muchong.com/t-2848680-1</url>
<Q><title>请问青基总共30页合适吗</title><apdx>请问青基总共30页合适吗，其中<br>（一）立项依据与研究内容，12页；<br>（二）研究基础与工作条件，12页。<apdx></Q>
<A><answer>太多了吧，兄弟！好好凝练一下！</answer><quality>0</quality><upvote>0</upvote><answer>太多了，20来页够了</answer><quality>0</quality><upvote>0</upvote><answer>研究基础那部分多了点，一般面上的也不过10来页</answer><quality>0</quality><upvote>1</upvote><answer>觉得挺多的</answer><quality>0</quality><upvote>0</upvote><answer>要注意字数限制</answer><quality>0</quality><upvote>0</upvote><answer>兄弟，863课题也不需要写这么多啊！</answer><quality>0</quality><upvote>1</upvote><answer>太多了<br>违反规则了</answer><quality>0</quality><upvote>0</upvote><answer>大家的经验丰富啊！</answer><quality>0</quality><upvote>0</upvote><answer>我也写了30页~</answer><quality>0</quality><upvote>0</upvote><answer>一般20来页就够了。</answer><quality>0</quality><upvote>0</upvote><answer>研究基础那部分多了点，一般面上的也不过10来页<br>学习了</answer><quality>0</quality><upvote>1</upvote><answer>我觉得不多啊，20多页能写出个啥来呢</answer><quality>0</quality><upvote>1</upvote><answer>你们可真能写呀，佩服佩服！</answer><quality>0</quality><upvote>1</upvote></A>
<url>http://muchong.com/t-2849041-1</url>
<Q><title>科学性提炼:化工的科学问题都包括哪些呢？</title><apdx>谢谢答复，我看看科学性提炼的对不对<apdx></Q>
<A><answer>你说的太笼统了，没办法回答。</answer><quality>0</quality><upvote>1</upvote><answer>9494</answer><quality>0</quality><upvote>0</upvote></A>
<url>http://muchong.com/t-2849656-1</url>
<Q><title>讲师青基还是副教青基呢</title><apdx>本人10年末评完副教还未公示，所以在写国青基金时是以讲师职称还是副教职称申请拿不定注意，大家能否给点建议。另外，以前以讲师身份有两个国家基金参与在研项目，会不会计入我今后申请基金限项中呢，谢谢！<apdx></Q>
<A><answer>讲师青基，因为副教授还没完成最终聘任。<br>参与的项目没有限项。</answer><quality>0</quality><upvote>1</upvote><answer>应该不会吧</answer><quality>0</quality><upvote>0</upvote><answer>如果在提交本子的时候已经公示，可以考虑用副教授！<br>主要考虑两点：能评上副教授也是科研能力的另一种实证；其二你很快就有自己的研究生，有人协助完成项目。</answer><quality>0</quality><upvote>1</upvote><answer>请问，如果我就按副教写，但是交本子时未公示，会有人查吗？谢谢！</answer><quality>0</quality><upvote>0</upvote><answer>如若还没有公示，改回讲师就可以，没必要给人留下话柄<br>真正重要的是本子！</answer><quality>0</quality><upvote>1</upvote><answer>应该写讲师。</answer><quality>0</quality><upvote>0</upvote><answer>在你交的那一刻还没出你评为副教授的文件就最好不要填副教授，只是交了评审材料不算数。因为很的学校，每年在评定高级职称交材料的人员里面，即使够了条件，也会淘汰一批。<br>希望楼主顺利通过。<br>另外，青基最重要是看创新，不是申请人的职称，所以职称还是实事求是好，</answer><quality>0</quality><upvote>1</upvote></A>
<url>http://muchong.com/t-2850456-1</url>
<Q><title>青年基金申请人员资格及人数怎样为好？</title><apdx>我博士毕业刚到该单位不久，是一国企，今年想申请青年科学基金，但参与人一处不知该如何填了。<br>这个项目如果能成也肯定主要是我来做，充其量会找一两个实习生来配合做一下实验，但这样是不是显得人员水平太低啊，被毙的可能大增呢。是不是一定要挂个高工之类的，总参与人数几个较为合适啊，望各位给个建议。多谢<br>我是博士学历，中级职称。<apdx></Q>
<A><answer>不注重团队，不要担心</answer><quality>0</quality><upvote>0</upvote><answer>哦，那就好，在企业里申请这个东西挂谁不挂谁都比较麻烦。</answer><quality>0</quality><upvote>0</upvote><answer>见过就一个申请人+两个学生的也成功了</answer><quality>0</quality><upvote>2</upvote></A>
<url>http://muchong.com/t-2850935-1</url>
<Q><title>2011版申请书从第五页开始没有版本号，你们的呢？</title><apdx>我检查保护打印后，发现从第五页到最后签名页都没版本号，你们是这样的吗？<apdx></Q>
<A><answer>是的</answer><quality>0</quality><upvote>0</upvote><answer>只有，2,3,4页才有版本号啊。<br>应该是这样的吧</answer><quality>0</quality><upvote>2</upvote><answer>确定吗？我以为我的申请书有问题。<br>记得前几年的基金申请书，每页都有号的。</answer><quality>0</quality><upvote>0</upvote><answer>去年好像就这样了</answer><quality>0</quality><upvote>0</upvote><answer>楼主，没问题，我的也这样！</answer><quality>0</quality><upvote>2</upvote><answer>谢谢！祝大家好运!</answer><quality>0</quality><upvote>0</upvote><answer></answer><quality>0</quality><upvote>0</upvote><answer></answer><quality>0</quality><upvote>1</upvote><answer>没问题，大家全是一样的</answer><quality>0</quality><upvote>1</upvote><answer>我试了，是的。<br>从第四页开始就没有版号了</answer><quality>0</quality><upvote>1</upvote></A>
<url>http://muchong.com/t-2843707-1</url>
<Q><title>青基关于申请人和参加人的工作时间问题。</title><apdx>假如，我申报了一项青年基金，我还要参与另外一项青年基金。<br>请问，我主持的项目每年工作时间是多少？参加的项目每年的工作时间是多少？<apdx></Q>
<A><answer>这个我也想问问，感谢好心虫友回答啊</answer><quality>0</quality><upvote>0</upvote><answer>4到8个月都行</answer><quality>0</quality><upvote>0</upvote></A>
<url>http://muchong.com/t-2851240-1</url>
<Q><title>青基的申请人简介问题</title><apdx>各位朋友好！今年青基的申请人简介跟以往是不是不同啊，以往要求写出所有参与者的简介，但今年的青基格式里怎么只要求写出申请人的了啊？我老板的简介是不是不用写了啊，他文章很多，还指望他压阵呢。<apdx></Q>
<A><answer>青年基金，<br>团队不是主要因素。</answer><quality>0</quality><upvote>0</upvote><answer>是啊，我居然没发现这个问题，还把其他人都弄进去了呢。到底要不要其他人的简介啊？<br>还有“申请人简介（包括申请人的学历和研究工作简历，近期已发表与本项目有关的主要论著目录和获得学术奖励情况。论著目录要求详细列出所有作者、论著题目、期刊名或出版社名、年、卷（期）、起止页码等；奖励情况也须详细列出全部受奖人员、奖励名称等级、授奖年等）”，这括号里的字要不要删掉呢？</answer><quality>0</quality><upvote>1</upvote><answer>这点跟以前不一样了！</answer><quality>0</quality><upvote>0</upvote><answer>跟以前不一样了，改吧</answer><quality>0</quality><upvote>0</upvote></A>
<url>http://muchong.com/t-2851125-1</url>
<Q><title>请问今年青年基金要写项目参与人的简介吗</title><apdx>请问今年青年基金要写项目参与人的简介吗？<br>去年的有明确要求，今年没有要求<apdx></Q>
<A><answer>我也没写参与人的呢</answer><quality>0</quality><upvote>0</upvote></A>
<url>http://muchong.com/t-2851199-1</url>
<Q><title>青基中关于申请资金数量</title><apdx>青基中关于申请资金数量，大家一般都申请多少呢。2011年规定每项25万元。大家一般都写多少呢，25万整，还是少于25万呢。<br>[]<apdx></Q>
<A><answer>25万吗？我从哪儿看到的最多资助30万，我写的28，难道错了？</answer><quality>0</quality><upvote>1</upvote><answer>我看的，青年基金每项最多25万。</answer><quality>0</quality><upvote>0</upvote><answer>好像是平均资助力度25w青年基金<br>没有说上限也没说下限估计30w以内都可以吧俺也是新手呵呵</answer><quality>0</quality><upvote>1</upvote></A>
<url>http://muchong.com/t-2851252-1</url>
<Q><title>中理论物理专项，还能申请青年项目吗？</title><apdx>各位牛人帮忙啊。<apdx></Q>
<A><answer>牛人啊，指点小弟一下吧。</answer><quality>0</quality><upvote>0</upvote><answer>可以的可以的<br>本文来自:小木虫论坛</answer><quality>0</quality><upvote>2</upvote><answer>作为负责人正在承担或者承担过青年科学基金项目的（包括资助期限1年的小额探索项目以及被终止或撤销的项目），不得再次申请。<br>===理论物理专项不属于青年科学基金项目，当然更不是青年基金中1年的小额探索项目了，按照这一条款，应该可以申请。<br>====但是，限项申请规定====<br>4．不具有高级专业技术职务（职称）人员的限项申请规定<br>　　作为申请人申请和作为负责人正在承担的项目数合计限为1项；在保证有足够的时间和精力参与项目研究工作的前提下，作为主要参与者申请或者承担各类型项目数量不限。<br>===========如果是讲师的话，这里的“合计限为1项”，不知道会不会影响申请青年基金？??</answer><quality>0</quality><upvote>1</upvote><answer>理论物理专款博士启动基金，是一年的，不在限项范围之内。所以可以拿到这个理论物理专款之后再申请青年基金，但是不能反过来。<br>这也是我所知道的讲师能主持两项国家自然科学基金的几个方法之一。另一个方法是一个数学天元基金加上一个青年基金或面上项目。<br>这是有实际例子的，所以请放心申请。</answer><quality>0</quality><upvote>2</upvote></A>
<url>http://muchong.com/t-2689013-1</url>
<Q><title>关于承担科研项目情况一栏</title><apdx>请问关于承担科研项目情况一栏，是否需要填写所有的项目<br>比如一些小项目如市厅级的等非国家级的在这里是否要填写？还是这里只要填国家级的，小级别的哪些只要在申请人简介中写就行了？<br>谢谢<apdx></Q>
<A><answer>这些可以写，也可以不写，这不是主要的，关键是你研究内容和方法要写好！</answer><quality>0</quality><upvote>0</upvote><answer>至少是省部级及以上的，一些小的项目不要写上去了！</answer><quality>0</quality><upvote>0</upvote></A>
<url>http://muchong.com/t-2851094-1</url>
<Q><title>关于青年基金的立项依据的问题！</title><apdx>2011年的青年基金的立项依据要求字数为4000-8000，是否包括参考文献？以前我看别人已经中的标书，一样也就两页，大概2500-3000字吧。<apdx></Q>
<A><answer>强人都写的短，弱人写的长，我写了1万多。<br>写2000左右可以，问题是你能保证评审专家一看到你的名字就有信心你做这个题目靠谱，<br>有这样的，我看到标题和申请人，我就觉得问题不大，因为以往看到他的文章太多了，都很靠谱。<br>这个就是立项依据，非常有依据。</answer><quality>0</quality><upvote>1</upvote><answer>呵呵，楼上说的有道理，我等菜牛还是写的详实一点的为好！</answer><quality>0</quality><upvote>1</upvote></A>
<url>http://muchong.com/t-2851077-1</url>
<Q><title>大家帮助看看那个题目好！！</title><apdx><apdx></Q>
<A><answer>第一个题目好一些，自然基金注重的是基础研究，技术研究支撑计划注重的东西</answer><quality>0</quality><upvote>0</upvote><answer>“***系统关键问题研究”</answer><quality>0</quality><upvote>0</upvote><answer>个人认为，问题研究比技术研究合适</answer><quality>0</quality><upvote>0</upvote><answer>这个题目看起来好大啊，像973了。</answer><quality>0</quality><upvote>0</upvote><answer>xx系统关键技术研究  一项技术比一些问题更有意义</answer><quality>0</quality><upvote>0</upvote><answer>两个都不好，题目太大了。</answer><quality>0</quality><upvote>0</upvote><answer>可以申报973了</answer><quality>0</quality><upvote>0</upvote><answer>系统是不是范围太大了？能不能进一步写的详细一些呢？</answer><quality>0</quality><upvote>0</upvote><answer>都不好，宜改小。</answer><quality>0</quality><upvote>0</upvote><answer>“***系统关键问题研究”的研究比较集中！</answer><quality>0</quality><upvote>0</upvote><answer>如果你用“系统”，后面较恰当的搭配是“技术”。<br>两个题目都不是很好，笼统了些。</answer><quality>0</quality><upvote>0</upvote></A>
<url>http://muchong.com/t-2849713-1</url>
<Q><title>博士点新教师基金与本博士点方向不是很一致可以不</title><apdx>博士点新教师基金与本博士点方向不是很一致可以不？<apdx></Q>
<A><answer>同样关心这个问题</answer><quality>0</quality><upvote>0</upvote></A>
<url>http://muchong.com/t-2851172-1</url>
<Q><title>理论物理限项吗？</title><apdx>请教大家一个问题，我是中级职称，按照2011年的申请指南说只能主持一项。目前我主持了理论物理博士启动项目，项目属于主任基金，只有12个月，对于副高来说是不计入限项的，但中级职称在指南中却没有提到，我们科研处的人说我受限了，不能申请今年的青年基金，我想听听大家的意见。<apdx></Q>
<A><answer>主任基金应该属于限项的。</answer><quality>0</quality><upvote>0</upvote><answer>讲师限，在研+参加小于等于1！</answer><quality>0</quality><upvote>0</upvote><answer>作为负责人正在承担或者承担过青年科学基金项目的（包括资助期限1年的小额探索项目以及被终止或撤销的项目），不得再次申请。<br>===理论物理专项不属于青年科学基金项目，当然更不是青年基金中1年的小额探索项目了，按照这一条款，应该可以申请。<br>====但是，限项申请规定====<br>4．不具有高级专业技术职务（职称）人员的限项申请规定<br>　　作为申请人申请和作为负责人正在承担的项目数合计限为1项；在保证有足够的时间和精力参与项目研究工作的前提下，作为主要参与者申请或者承担各类型项目数量不限。<br>===========如果是讲师的话，这里的“合计限为1项”，不知道会不会影响申请青年基金？??</answer><quality>0</quality><upvote>0</upvote></A>
<url>http://muchong.com/t-2785245-1</url>
<Q><title>技术路线中的参考文献，如果有的话，列哪里？</title><apdx>如题，假如技术路线中也要引用参考文献，列哪里比较合适？<apdx></Q>
<A><answer>可直接写出</answer><quality>0</quality><upvote>0</upvote><answer>文中用括号表明，写上第一作者，然后注明期刊、页码等基本信息，文题可略</answer><quality>0</quality><upvote>1</upvote><answer>呵呵，遇到同样问题，受教了，多谢！</answer><quality>0</quality><upvote>1</upvote><answer>在研究方法和技术路线中有参考文献，我的做法是，删掉，不写了。</answer><quality>0</quality><upvote>1</upvote><answer>zui最好不要有</answer><quality>0</quality><upvote>0</upvote><answer>刚要发帖咨询，发现楼主先问了</answer><quality>0</quality><upvote>1</upvote></A>
<url>http://muchong.com/t-2850474-1</url>
<Q><title>关键词与送审专家</title><apdx>那位虫友了解，关键词决定送审专家吗？<br>有什么关系？<apdx></Q>
<A><answer>一般是学科代码决定</answer><quality>0</quality><upvote>1</upvote><answer>没什么关系</answer><quality>0</quality><upvote>0</upvote><answer>学科代码更确切---------</answer><quality>0</quality><upvote>1</upvote><answer>应该是看学科代码</answer><quality>0</quality><upvote>0</upvote></A>
<url>http://muchong.com/t-2850596-1</url>
<Q><title>请教：初步实验结果应该放在哪里</title><apdx>是研究方案和可行性分析，还是工作基础？<br>多谢！<apdx></Q>
<A><answer>工作基础</answer><quality>0</quality><upvote>0</upvote><answer>放在立论依据、工作基础都可以，</answer><quality>0</quality><upvote>1</upvote><answer>初步实验结果可以放在工作基础中</answer><quality>0</quality><upvote>1</upvote><answer>工作基础</answer><quality>0</quality><upvote>0</upvote><answer>个人感觉放在“立项依据”里比较好</answer><quality>0</quality><upvote>0</upvote><answer>立项依据里内容是不是太多了，现在加参考文献已经5页了。。。</answer><quality>0</quality><upvote>0</upvote><answer>在工作基础部分讲得稍微详细些，在可行性分析部分概括提一下，效果更好！</answer><quality>0</quality><upvote>1</upvote><answer>嗯，这个建议不错，多谢！</answer><quality>0</quality><upvote>0</upvote><answer>太多了，谁有空看，建议减到2页内！</answer><quality>0</quality><upvote>1</upvote><answer>严重赞同</answer><quality>0</quality><upvote>0</upvote><answer>有道理，参考文献太多反而显得多余。</answer><quality>0</quality><upvote>1</upvote><answer>我是放在立项依据里介绍自己的原有工作的。</answer><quality>0</quality><upvote>1</upvote></A>
<url>http://muchong.com/t-2848286-1</url>
<Q><title>讲师，有青基，能申请面上么？</title><apdx>讲师，有青基，能申请面上么？<br>一直对这个有疑惑，请指教！<apdx></Q>
<A><answer>可以，只要你不超项</answer><quality>0</quality><upvote>0</upvote><answer>中级职称限制多少项啊？</answer><quality>0</quality><upvote>0</upvote><answer>指南中好像没有对中级职称主持项目的限项规定，期待专家正解。。。</answer><quality>0</quality><upvote>0</upvote><answer>中级职称只能主持1项，可以参加无穷多项</answer><quality>0</quality><upvote>1</upvote><answer>青基还没结题都不能申请的呢</answer><quality>0</quality><upvote>1</upvote><answer>呵呵，建议去看下基金指南吧。</answer><quality>0</quality><upvote>1</upvote><answer>青基没结题之前，只要你依然是讲师职称，那你就什么也不能报。</answer><quality>0</quality><upvote>0</upvote><answer>正解</answer><quality>0</quality><upvote>0</upvote><answer>不能，中级职称只能主持一项（任何一项都计）。今年可以报，但肯定超项。</answer><quality>0</quality><upvote>1</upvote><answer>肯定不能申请了！中级只能主持一项</answer><quality>0</quality><upvote>1</upvote><answer>显然不能，咱们一样哈哈，中级职称害得。</answer><quality>0</quality><upvote>1</upvote><answer>buneng</answer><quality>0</quality><upvote>0</upvote><answer>添句废话，不能主持，只能参与！</answer><quality>0</quality><upvote>0</upvote></A>
<url>http://muchong.com/t-2848681-1</url>
<Q><title>创新性感觉不够，但有地区特色，有实用价值的选题可以不？</title><apdx>本人在新疆，选的是有特色的地域资源，用的是遥感技术，创新性不强，有的好多是前人的技术，以解决实际应用问题为主，实用性很强，想报地区基金，不知道这样的选题合适不？<apdx></Q>
<A><answer>感觉不太好，自然基金主要赞助基础研究。应用类的是973啥的</answer><quality>0</quality><upvote>1</upvote><answer>祝福！！</answer><quality>0</quality><upvote>0</upvote><answer>不试肯定不行。在实用性基础上加些理论的吧</answer><quality>0</quality><upvote>0</upvote></A>
<url>http://muchong.com/t-2850383-1</url>
<Q><title>项目参加人在外在职攻读博士，还需要其导师同意函吗？</title><apdx>青年基金的项目参加人员(不是项目申请的负责人)是本校人员，在外在职攻读博士，要是把他写成在读博士的话，还需要其导师同意函吗？<apdx></Q>
<A><answer>不需要的。<br>导师同意函是针对在读博士本人作为负责人申请时用的。<br>只有你（负责人）够基金委的条件就好。</answer><quality>0</quality><upvote>1</upvote><answer>非常感谢您！<br>我想法转给你两个金币。呵呵</answer><quality>0</quality><upvote>0</upvote></A>
<url>http://muchong.com/t-2850536-1</url>
<Q><title>青年基金标书中讲师的职称应写初级吗</title><apdx>青年基金标书中讲师的职称应写初级吗?是初级还是中级啊？谢谢！<apdx></Q>
<A><answer>讲师是中级职称，职称就写讲师</answer><quality>0</quality><upvote>2</upvote><answer>如果你的是讲师，那么应该是中级</answer><quality>0</quality><upvote>1</upvote><answer>中级</answer><quality>0</quality><upvote>0</upvote><answer>晕倒，讲师当然是中级啊，不过助理研究员也是中级哈</answer><quality>0</quality><upvote>1</upvote><answer>中级，不用怀疑！</answer><quality>0</quality><upvote>0</upvote><answer>晕，你是怎么评上讲师的</answer><quality>0</quality><upvote>0</upvote><answer>喷！晕！</answer><quality>0</quality><upvote>0</upvote><answer>讲师当然是中级啊</answer><quality>0</quality><upvote>0</upvote><answer>中级<br>本文来自:小木虫论坛</answer><quality>0</quality><upvote>1</upvote></A>
<url>http://muchong.com/t-2850283-1</url>
<Q><title>基金申请书中的办公电话问题</title><apdx>我今年刚毕业，没有办公室，办公电话可不可以填手机啊？<apdx></Q>
<A><answer>可以</answer><quality>0</quality><upvote>0</upvote><answer>谢谢啊！</answer><quality>0</quality><upvote>0</upvote><answer>大部分青椒都存在该问题，哎，没有办法，我们学校一线教师都没有办公室</answer><quality>0</quality><upvote>1</upvote><answer>一般人家联系都是和手机联系，如果手机实在联系不上了才打所谓的办公室电话</answer><quality>0</quality><upvote>0</upvote></A>
<url>http://muchong.com/t-2850355-1</url>
